DataProfileViewerAKP/DataProfileViewerAKP.py
DataProfileViewerAKP/TestModule.py
DataProfileViewerAKP/__init__.py
DataProfileViewerAKP-0.1.9.dist-info/METADATA
DataProfileViewerAKP-0.1.9.dist-info/WHEEL
DataProfileViewerAKP-0.1.9.dist-info/top_level.txt
DataProfileViewerAKP-0.1.9.dist-info/RECORD
